haferml/__init__.py
haferml/command.py
haferml/version.py
haferml/blend/__init__.py
haferml/blend/config.py
haferml/data/__init__.py
haferml/data/wrangle/__init__.py
haferml/data/wrangle/datetime.py
haferml/data/wrangle/misc.py
haferml/etl/__init__.py
haferml/etl/extract/__init__.py
haferml/etl/transform/__init__.py
haferml/etl/transform/ingredients.py
haferml/etl/transform/pipeline.py
haferml/lab/__init__.py
haferml/model/__init__.py
haferml/model/dataset.py
haferml/model/modelset.py
haferml/model/pipeline.py
haferml/model/workflow.py
haferml/preprocess/__init__.py
haferml/preprocess/ingredients.py
haferml/preprocess/pipeline.py
haferml/sync/__init__.py
haferml/sync/aws.py
haferml/sync/local.py
haferml/utils/__init__.py
haferml/utils/sugar.py
haferml-0.0.13.dist-info/LICENSE
haferml-0.0.13.dist-info/METADATA
haferml-0.0.13.dist-info/WHEEL
haferml-0.0.13.dist-info/entry_points.txt
haferml-0.0.13.dist-info/top_level.txt
haferml-0.0.13.dist-info/RECORD
